jqdatahttp.py
jqdatahttp-0.1.6.dist-info/LICENSE
jqdatahttp-0.1.6.dist-info/METADATA
jqdatahttp-0.1.6.dist-info/WHEEL
jqdatahttp-0.1.6.dist-info/top_level.txt
jqdatahttp-0.1.6.dist-info/RECORD
