Metadata-Version: 2.1
Name: jqdatahttp
Version: 0.1.6
Summary: JQData HTTP API encapsulation
Home-page: https://github.com/kuanghy/jqdatahttp
Author: Huoty
Author-email: sudohuoty@163.com
Maintainer: Huoty
Maintainer-email: sudohuoty@163.com
License: Apache License v2
Keywords: jqdata,jqdatahttp,jq,joinquant
Platform: any
Classifier: Development Status :: 4 - Beta
Classifier: Programming Language :: Python
Classifier: Programming Language :: Python :: 3
Classifier: License :: OSI Approved :: Apache Software License
Requires-Python: >=3.6
Provides-Extra: whole
Requires-Dist: numpy ; extra == 'whole'
Requires-Dist: pandas ; extra == 'whole'
